wyge/__init__.py
wyge/agents/__init__.py
wyge/agents/react_agent.py
wyge/agents/teaching_agent.py
wyge/common/__init__.py
wyge/common/logger.py
wyge/memory/__init__.py
wyge/memory/basic_memory.py
wyge/models/__init__.py
wyge/models/openai_models.py
wyge/prebuilt_agents/__init__.py
wyge/prebuilt_agents/generating_syllabus.py
wyge/prebuilt_agents/mcq_generator.py
wyge/prebuilt_agents/medical_diagnosis.py
wyge/prebuilt_agents/medical_image_processing.py
wyge/prebuilt_agents/multimodal_rag.py
wyge/prebuilt_agents/pdf_extractor.py
wyge/prebuilt_agents/rag.py
wyge/prebuilt_agents/resume_analyser.py
wyge/prebuilt_agents/social_media_agents.py
wyge/prebuilt_agents/sql.py
wyge/prebuilt_agents/synthetic_data_generator.py
wyge/prebuilt_agents/teaching_agent.py
wyge/prebuilt_agents/travel_planner.py
wyge/prebuilt_agents/vqa.py
wyge/tools/__init__.py
wyge/tools/base_tool.py
wyge/tools/generating_syllabus.py
wyge-1.1.16.dist-info/METADATA
wyge-1.1.16.dist-info/WHEEL
wyge-1.1.16.dist-info/top_level.txt
wyge-1.1.16.dist-info/RECORD
