Metadata-Version: 2.2
Name: wyge
Version: 1.1.16
Summary: A Python library for WYGE
Home-page: https://github.com/prudvireddyNS/vyzeai
Author: Prudvi
Author-email: prudhvisneha2003@gmail.com
Classifier: Programming Language :: Python :: 3
Classifier: License :: OSI Approved :: MIT License
Classifier: Operating System :: OS Independent
Requires-Python: >=3.8
Requires-Dist: openai
Requires-Dist: requests
Requires-Dist: numpy
Requires-Dist: pydantic[email]
Requires-Dist: langchain
Provides-Extra: dev
Requires-Dist: pytest>=7.0; extra == "dev"
Requires-Dist: twine>=4.0.2; extra == "dev"
Dynamic: author
Dynamic: author-email
Dynamic: classifier
Dynamic: description-content-type
Dynamic: home-page
Dynamic: provides-extra
Dynamic: requires-dist
Dynamic: requires-python
Dynamic: summary
